RubyYuanmaJiedu/README.md
RubyYuanmaJiedu/__init__.py
RubyYuanmaJiedu/__main__.py
RubyYuanmaJiedu/file.epub
RubyYuanmaJiedu/index.html
RubyYuanmaJiedu/css/__init__.py
RubyYuanmaJiedu/css/annotations.css
RubyYuanmaJiedu/css/main.css
RubyYuanmaJiedu/css/normalize.css
RubyYuanmaJiedu/css/popup.css
RubyYuanmaJiedu/font/__init__.py
RubyYuanmaJiedu/font/fontello.eot
RubyYuanmaJiedu/font/fontello.svg
RubyYuanmaJiedu/font/fontello.ttf
RubyYuanmaJiedu/font/fontello.woff
RubyYuanmaJiedu/img/__init__.py
RubyYuanmaJiedu/img/annotator-glyph-sprite.png
RubyYuanmaJiedu/img/annotator-icon-sprite.png
RubyYuanmaJiedu/img/apple-touch-icon.png
RubyYuanmaJiedu/img/cancelfullscreen.png
RubyYuanmaJiedu/img/close.png
RubyYuanmaJiedu/img/fullscreen.png
RubyYuanmaJiedu/img/loader.gif
RubyYuanmaJiedu/img/menu-icon.png
RubyYuanmaJiedu/img/save.png
RubyYuanmaJiedu/img/saved.png
RubyYuanmaJiedu/img/settings-s.png
RubyYuanmaJiedu/img/settings.png
RubyYuanmaJiedu/img/star.png
RubyYuanmaJiedu/js/__init__.py
RubyYuanmaJiedu/js/epub.js
RubyYuanmaJiedu/js/epub.min.js
RubyYuanmaJiedu/js/epub.min.map
RubyYuanmaJiedu/js/hooks.min.js
RubyYuanmaJiedu/js/hooks.min.map
RubyYuanmaJiedu/js/reader.js
RubyYuanmaJiedu/js/reader.js.map
RubyYuanmaJiedu/js/reader.min.js
RubyYuanmaJiedu/js/reader.min.map
RubyYuanmaJiedu/js/hooks/__init__.py
RubyYuanmaJiedu/js/hooks/extensions/__init__.py
RubyYuanmaJiedu/js/hooks/extensions/highlight.js
RubyYuanmaJiedu/js/libs/__init__.py
RubyYuanmaJiedu/js/libs/jquery.min.js
RubyYuanmaJiedu/js/libs/localforage.min.js
RubyYuanmaJiedu/js/libs/screenfull.js
RubyYuanmaJiedu/js/libs/screenfull.min.js
RubyYuanmaJiedu/js/libs/zip.min.js
RubyYuanmaJiedu/js/plugins/__init__.py
RubyYuanmaJiedu/js/plugins/hypothesis.js
RubyYuanmaJiedu/js/plugins/search.js
ruby_yuanma_jiedu-2024.3.2.0.dist-info/METADATA
ruby_yuanma_jiedu-2024.3.2.0.dist-info/WHEEL
ruby_yuanma_jiedu-2024.3.2.0.dist-info/entry_points.txt
ruby_yuanma_jiedu-2024.3.2.0.dist-info/top_level.txt
ruby_yuanma_jiedu-2024.3.2.0.dist-info/RECORD
